{
  "version": 3,
  "status": "ok",
  "generatedAt": "2026-07-20T12:17:46.781189Z",
  "lastCheckedAt": "2026-07-20T12:17:46.781189Z",
  "source": "Investor Control multi-market near-live feed",
  "error": null,
  "fxRates": {
    "EURUSD": {
      "rate": 1.1424654722213745,
      "updatedAt": "2026-07-20T12:17:21Z",
      "source": "Yahoo Finance latest 1-minute bar (unofficial)"
    }
  },
  "quotes": {
    "ALWN.GR": {
      "price": 13.21500015258789,
      "previousClose": 13.0,
      "updatedAt": "2026-07-20T12:01:57Z",
      "checkedAt": "2026-07-20T12:17:46.781189Z",
      "delaySeconds": 949,
      "source": "Yahoo Finance latest 1-minute bar (unofficial)",
      "providerSymbol": "ALWN.AT",
      "marketState": null,
      "currency": "EUR",
      "nativePrice": 13.21500015258789,
      "nativePreviousClose": 13.0,
      "nativeCurrency": "EUR",
      "fxRate": 1.0,
      "changePct": 1.6538473275991585
    },
    "SPCE.US": {
      "price": 2.240767887542331,
      "previousClose": 2.2670269368964684,
      "updatedAt": "2026-07-17T20:00:00Z",
      "checkedAt": "2026-07-20T12:17:46.781189Z",
      "delaySeconds": 231466,
      "source": "Yahoo Finance latest 1-minute bar (unofficial) · converted USD→EUR with EURUSD=X",
      "providerSymbol": "SPCE",
      "marketState": null,
      "currency": "EUR",
      "fxRate": 1.1424654722213745,
      "nativePrice": 2.559999942779541,
      "nativePreviousClose": 2.59,
      "nativeCurrency": "USD",
      "changePct": -1.1583033675852834
    }
  },
  "summary": {
    "fresh": 2,
    "stale": 0,
    "symbols": [
      "ALWN.GR",
      "SPCE.US"
    ]
  }
}
