{
  "version": 3,
  "status": "ok",
  "generatedAt": "2026-07-22T17:52:43.183451Z",
  "lastCheckedAt": "2026-07-22T17:52:43.183451Z",
  "source": "Investor Control multi-market near-live feed",
  "error": null,
  "fxRates": {
    "EURUSD": {
      "rate": 1.141422152519226,
      "updatedAt": "2026-07-22T17:52:20Z",
      "source": "Yahoo Finance latest 1-minute bar (unofficial)"
    }
  },
  "quotes": {
    "ALWN.GR": {
      "price": 13.029999732971191,
      "previousClose": 13.275,
      "updatedAt": "2026-07-22T14:16:00Z",
      "checkedAt": "2026-07-22T17:52:43.183451Z",
      "delaySeconds": 13003,
      "source": "Yahoo Finance latest 1-minute bar (unofficial)",
      "providerSymbol": "ALWN.AT",
      "marketState": null,
      "currency": "EUR",
      "nativePrice": 13.029999732971191,
      "nativePreviousClose": 13.275,
      "nativeCurrency": "EUR",
      "fxRate": 1.0,
      "changePct": -1.8455763994637209
    },
    "SPCE.US": {
      "price": 2.374231157302973,
      "previousClose": 2.4355581270823228,
      "updatedAt": "2026-07-22T17:52:39Z",
      "checkedAt": "2026-07-22T17:52:43.183451Z",
      "delaySeconds": 4,
      "source": "Yahoo Finance latest 1-minute bar (unofficial) · converted USD→EUR with EURUSD=X",
      "providerSymbol": "SPCE",
      "marketState": null,
      "currency": "EUR",
      "fxRate": 1.141422152519226,
      "nativePrice": 2.7100000381469727,
      "nativePreviousClose": 2.78,
      "nativeCurrency": "USD",
      "changePct": -2.517984239317524
    }
  },
  "summary": {
    "fresh": 2,
    "stale": 0,
    "symbols": [
      "ALWN.GR",
      "SPCE.US"
    ]
  }
}
